{
  "english": "deficit",
  "phat_am": "ˈdefisit",
  "list_english": [
    {
      "type_word": "noun",
      "list_definition": [
        {
          "mean_english": "số tiền thiếu hụt",
          "definition": "the amount by which an amount (of money etc) is less than the amount required",
          "world_new": [
            "amount",
            "amount",
            "money",
            "amount"
          ],
          "list_ex_of_definition": [
            {
              "ex_of_definition": "a trade deficit",
              "world_new": [
                "trade"
              ]
            },
            {
              "ex_of_definition": "a deficit of several hundred dollars."
            }
          ]
        }
      ]
    }
  ],
  "list_ex_of_english": [
    "The answer should provide an evaluation of the role of memory in the symbolic deficits found in children with autism.",
    "In this study it is unclear whether marital violence, family upheaval, or homelessness accounts for the observed deficits in children's social competence.",
    "This overvalued the currency, causing an increase in imports and thus a current-account deficit.",
    "However, the exact relationship of these cognitive deficits to catatonic symptoms remains unclear.",
    "The cooling paradigm also permitted rapid reversal and repeated demonstration of deficits in the same testing session.",
    "In practice the pace of expenditure and deficit reduction was in advance of that planned and as a consequence tax relaxation was possible.",
    "But, in fact, his input and output deficits match one another very precisely, suggesting a deficit in underlying competence.",
    "However, it was unclear how these deficits would manifest with increasing child age."
  ],
  "list_see_also": [],
  "list_browse": [
    "defiant",
    "defiantly",
    "deficiency",
    "deficient",
    "deficit",
    "definable",
    "define",
    "definite",
    "definite article"
  ],
  "list_img": [
    {
      "link_thumb": "https://live.staticflickr.com/65535/51809661224_90f96fc41b_n.jpg",
      "link_img": "https://live.staticflickr.com/65535/51809661224_503d6225da_o.png",
      "id_image": "deficit_2112495"
    }
  ]
}